kline/__init__.py
kline/base.py
kline/ccxt.py
kline/cli.py
kline/deribit.py
kline/max.py
kline/py.typed
kline/utils.py
kline-0.5.1.dist-info/METADATA
kline-0.5.1.dist-info/WHEEL
kline-0.5.1.dist-info/entry_points.txt
kline-0.5.1.dist-info/licenses/LICENSE
kline-0.5.1.dist-info/RECORD
